setup.py
toTrello.egg-info/PKG-INFO
toTrello.egg-info/SOURCES.txt
toTrello.egg-info/dependency_links.txt
toTrello.egg-info/entry_points.txt
toTrello.egg-info/requires.txt
toTrello.egg-info/top_level.txt
trello_tool/__init__.py
trello_tool/__main__.py