Metadata-Version: 1.0
Name: toTrello
Version: 0.0.5
Summary: publish work flow to trello
Home-page: https://github.com/LogosFu/trello-tool
Author: LogosFu
Author-email: logosfu@gmail.com
License: GNU General Public License v3.0
Platform: UNKNOWN
